{"name":"Framebold","tagline":"Desenvolvido a partir de problemas diários.","body":"### Framebold\r\nConsidere o Framebold como um template de pré-projetos que utilizo no meu dia-a-dia. <br>\r\nCom ele você terá acesso a organização dos meus diretórios, alguns plugins que utilizo, assim como uma estrutura de HTML, um CSS já com algumas coisas que utilizo e umas configurações em diversos arquivos que tenho como base para início de projeto.\r\n\r\n### Instalação\r\n`cd minha-pasta-de-projetos` <br>\r\n`git clone https://github.com/thulioph/framebold.git`\r\n\r\n### Esqueleto\r\nEstrutura do template <br>\r\n\r\n```\r\n├── arquivos\r\n├── css\r\n│   ├── main.css\r\n│   └── plugins\r\n│       └── css-do-plugin\r\n│   └── fonts\r\n│       └── pasta-nome-da-font\r\n├── img\r\n├── inc\r\n│   └── head.inc.php\r\n├── js\r\n│   ├── main.js\r\n│   └── vendor\r\n│       ├── modernizr.min.js\r\n│       ├── colorbox.min.js\r\n│       ├── head.min.js\r\n│       ├── jquery-1.9.1.js\r\n│       ├── jquery.cycle.all.js\r\n│       ├── jquery.lazyload.min.js\r\n│       └── mask_input.js\r\n├── .htaccess\r\n├── .gitignore\r\n├── 404.html\r\n├── apple-touch-icon-ipad.png\r\n├── apple-touch-icon-iphone4.png\r\n├── apple-touch-icon.png\r\n├── favicon.ico\r\n├── humans.txt\r\n├── README.md\r\n└── index.php\r\n```\r\n\r\n### Resumo do diretório\r\n* arquivos - todos os arquivos relacionados com o projeto; <br>\r\n* css - todo o css envolvido no projeto, as subpastas são para o css dos plugins e as fonts ficam em uma pasta a parte; <br>\r\n* img - todas as imagens que serão utilizadas no projeto; <br>\r\n* inc - diretório contendo os includes; <br>\r\n* js - todo javascript utilizado no projeto ficará no arquivo `main.js` e a pasta vendor irá conter os plugins utilizados ; <br>\r\n* .htaccess - arquivo de configuração do servidor apache; <br>\r\n* humans.txt - informações sobre membros envolvidos no projeto, tecnologia utilizada, última atualização, etc..;\r\n\r\n\r\n### Como contribuir?\r\n1. Faça um fork deste projeto!\r\n2. Crie uma branch com sua melhorias: `git checkout -b minhas-melhorias`\r\n3. Commit suas alterações: `git commit -am 'Minhas alterações'`\r\n4. Dê um push na branch: `git push origin minhas-melhorias`\r\n5. Envie um pull request.","google":"","note":"Don't delete this file! It's used internally to help with page regeneration."}